{
  "wallets": [
    {
      "address": "8zhsjqPCZAY9g8bySFery1kX8hixJC1Q31C136K7NGv7",
      "balance": 868181105.12425,
      "percentage": 86.82,
      "rank": 1,
      "addedAt": "2025-09-27T07:13:18.504Z",
      "lastSeen": "2025-09-27T07:13:18.504Z",
      "updateCount": 1
    },
    {
      "address": "EvL3WNCGSDmUKQLpBgFBLfqzJVxweo1s3xBUfP4wDz6s",
      "balance": 37839456.361678,
      "percentage": 3.78,
      "rank": 2,
      "addedAt": "2025-09-27T07:13:18.504Z",
      "lastSeen": "2025-09-27T07:13:18.504Z",
      "updateCount": 1
    },
    {
      "address": "4zgbVKpNW4vbRv4o773zP92CsCjvUhttuGLPA7Yvp6dE",
      "balance": 28048076.511791,
      "percentage": 2.8,
      "rank": 3,
      "addedAt": "2025-09-27T07:13:18.504Z",
      "lastSeen": "2025-09-27T07:13:18.504Z",
      "updateCount": 1
    },
    {
      "address": "9EMid2bjMS9pedxRCasM9pNSMWXVfqAzyBkYbeDDw35f",
      "balance": 12717655.621068,
      "percentage": 1.27,
      "rank": 4,
      "addedAt": "2025-09-27T07:13:18.504Z",
      "lastSeen": "2025-09-27T07:13:18.504Z",
      "updateCount": 1
    },
    {
      "address": "5tmuJKGJ5erVzZGH7CnrBUhyC998caQQuaQHPb9UJvhv",
      "balance": 9237420.798171,
      "percentage": 0.92,
      "rank": 5,
      "addedAt": "2025-09-27T07:13:18.504Z",
      "lastSeen": "2025-09-27T07:13:18.504Z",
      "updateCount": 1
    },
    {
      "address": "BtzUBj2dTwghjWRFHr25iWEp9Myx1tnnSyiFUtNBL1wf",
      "balance": 7651697.404986,
      "percentage": 0.77,
      "rank": 6,
      "addedAt": "2025-09-27T07:13:18.504Z",
      "lastSeen": "2025-09-27T07:13:18.504Z",
      "updateCount": 1
    },
    {
      "address": "6kwGzcQZxE3s7QrJG2ajbPL8886qEZEUoRZL1QKXFRHy",
      "balance": 6465902.556158,
      "percentage": 0.65,
      "rank": 7,
      "addedAt": "2025-09-27T07:13:18.504Z",
      "lastSeen": "2025-09-27T07:13:18.504Z",
      "updateCount": 1
    },
    {
      "address": "8cD35aBeoEbcsZtuV8W93Hj2ktm8xh4QnWuPoLPaDucr",
      "balance": 4928675.299787,
      "percentage": 0.49,
      "rank": 8,
      "addedAt": "2025-09-27T07:13:18.504Z",
      "lastSeen": "2025-09-27T07:13:18.504Z",
      "updateCount": 1
    },
    {
      "address": "5cKnV9jz344fgfqCvbGxtKqwRgeifUYs9bhxCHTL8Det",
      "balance": 1671820.055276,
      "percentage": 0.17,
      "rank": 9,
      "addedAt": "2025-09-27T07:13:18.504Z",
      "lastSeen": "2025-09-27T07:13:18.504Z",
      "updateCount": 1
    },
    {
      "address": "8SLVdEwcEupvSm6Fwvhes8fkU6VQHJKj5jBownhk1HFe",
      "balance": 1666380.503164,
      "percentage": 0.17,
      "rank": 10,
      "addedAt": "2025-09-27T07:13:18.504Z",
      "lastSeen": "2025-09-27T07:13:18.504Z",
      "updateCount": 1
    },
    {
      "address": "DDHJ5MnKEBgLRwTALzfLAeGsSubSr4Jkk7XiabhPpz3M",
      "balance": 1613355.551848,
      "percentage": 0.16,
      "rank": 11,
      "addedAt": "2025-09-27T07:13:18.504Z",
      "lastSeen": "2025-09-27T07:13:18.504Z",
      "updateCount": 1
    },
    {
      "address": "83iMVNYTKFGFR8otNiG92F7kHZZRPDET3MwKcf9SSyNX",
      "balance": 1491502.036187,
      "percentage": 0.15,
      "rank": 12,
      "addedAt": "2025-09-27T07:13:18.504Z",
      "lastSeen": "2025-09-27T07:13:18.504Z",
      "updateCount": 1
    },
    {
      "address": "He8fTSazXRRqNbg4QG9dXtzXFJgcxa1MVcFYBDYTynuQ",
      "balance": 1391075.974611,
      "percentage": 0.14,
      "rank": 13,
      "addedAt": "2025-09-27T07:13:18.504Z",
      "lastSeen": "2025-09-27T07:13:18.504Z",
      "updateCount": 1
    },
    {
      "address": "9gWgTFQXbsfkRppCwkGEeLj4qxbGg7mUFpT3H6b3WcjG",
      "balance": 1329230.495063,
      "percentage": 0.13,
      "rank": 14,
      "addedAt": "2025-09-27T07:13:18.504Z",
      "lastSeen": "2025-09-27T07:13:18.504Z",
      "updateCount": 1
    },
    {
      "address": "DdqKEFeBpEKnCaNsjJnfKqbbTiF18CySWw8mtQzuu1RL",
      "balance": 1287488.834378,
      "percentage": 0.13,
      "rank": 15,
      "addedAt": "2025-09-27T07:13:18.504Z",
      "lastSeen": "2025-09-27T07:13:18.504Z",
      "updateCount": 1
    },
    {
      "address": "BkjYnDMYTMB7zFmqWKUEULcE4S5o3uhfPsd4aRRPexiA",
      "balance": 1277229.322071,
      "percentage": 0.13,
      "rank": 16,
      "addedAt": "2025-09-27T07:13:18.504Z",
      "lastSeen": "2025-09-27T07:13:18.504Z",
      "updateCount": 1
    },
    {
      "address": "86XKrKrkscp5kpoSnPPzdRMKJfwaChCr9Yqwuu53Lrax",
      "balance": 1228685.092572,
      "percentage": 0.12,
      "rank": 17,
      "addedAt": "2025-09-27T07:13:18.504Z",
      "lastSeen": "2025-09-27T07:13:18.504Z",
      "updateCount": 1
    },
    {
      "address": "Gme2ihEXgs1rmUnumLr256B1gFeHU1eJGqMcdZZWjfZy",
      "balance": 1217788.56855,
      "percentage": 0.12,
      "rank": 18,
      "addedAt": "2025-09-27T07:13:18.504Z",
      "lastSeen": "2025-09-27T07:13:18.504Z",
      "updateCount": 1
    },
    {
      "address": "Eqc5DHVMACkMpZu1gUispQLammF1E5yQUs3porviWxND",
      "balance": 1075912.540598,
      "percentage": 0.11,
      "rank": 19,
      "addedAt": "2025-09-27T07:13:18.504Z",
      "lastSeen": "2025-09-27T07:13:18.504Z",
      "updateCount": 1
    },
    {
      "address": "ATQhGf9hbx8RDrZW6RnrTNALPDQwkubMWuD8s9zqbkiD",
      "balance": 836056.601783,
      "percentage": 0.08,
      "rank": 20,
      "addedAt": "2025-09-27T07:13:18.504Z",
      "lastSeen": "2025-09-27T07:13:18.504Z",
      "updateCount": 1
    },
    {
      "address": "74KbMqaCRaAKLhp86niWrumfiVHhB1SvVK2i3LdmGssg",
      "balance": 821708.651303,
      "percentage": 0.08,
      "rank": 21,
      "addedAt": "2025-09-27T07:13:18.504Z",
      "lastSeen": "2025-09-27T07:13:18.504Z",
      "updateCount": 1
    },
    {
      "address": "47EAKHWabEEw2q8WbNKhiA3dERrq5SMSCo5WJhXzX9kV",
      "balance": 658821.44194,
      "percentage": 0.07,
      "rank": 22,
      "addedAt": "2025-09-27T07:13:18.504Z",
      "lastSeen": "2025-09-27T07:13:18.504Z",
      "updateCount": 1
    },
    {
      "address": "2rvR7Rdshu1Erf4Q89TTySXjdGd2tyREabnuxzbWZvEr",
      "balance": 636866.341873,
      "percentage": 0.06,
      "rank": 23,
      "addedAt": "2025-09-27T07:13:18.504Z",
      "lastSeen": "2025-09-27T07:13:18.504Z",
      "updateCount": 1
    },
    {
      "address": "2eSU3g2uZSGCcTqb3LribBXLkS3FAiUVVxFsTYgMSna2",
      "balance": 634996.141636,
      "percentage": 0.06,
      "rank": 24,
      "addedAt": "2025-09-27T07:13:18.504Z",
      "lastSeen": "2025-09-27T07:13:18.504Z",
      "updateCount": 1
    },
    {
      "address": "HP1jJ3YbJZbrEcuAeTL2ZmPSmUpQJmPjmGnqfXNMSvDf",
      "balance": 624943.930104,
      "percentage": 0.06,
      "rank": 25,
      "addedAt": "2025-09-27T07:13:18.504Z",
      "lastSeen": "2025-09-27T07:13:18.504Z",
      "updateCount": 1
    },
    {
      "address": "HhFooxagu5o2YsdX3xgkfz916ehu6SfAFTQ6EPwx5iD3",
      "balance": 593909.178714,
      "percentage": 0.06,
      "rank": 26,
      "addedAt": "2025-09-27T07:13:18.504Z",
      "lastSeen": "2025-09-27T07:13:18.504Z",
      "updateCount": 1
    },
    {
      "address": "GsYYNtfTw3bpsXeMgLiAVYgQXd5JaoQ6ejuhnabmRGPn",
      "balance": 567394.466741,
      "percentage": 0.06,
      "rank": 27,
      "addedAt": "2025-09-27T07:13:18.504Z",
      "lastSeen": "2025-09-27T07:13:18.504Z",
      "updateCount": 1
    },
    {
      "address": "8yVgUn3inPEtjaZNLqNGKVRWQJ1tDaVimY4PJKYJqfYm",
      "balance": 563615.83553,
      "percentage": 0.06,
      "rank": 28,
      "addedAt": "2025-09-27T07:13:18.504Z",
      "lastSeen": "2025-09-27T07:13:18.504Z",
      "updateCount": 1
    },
    {
      "address": "BjZ7PYmr6YDCAiNqLN6SDX4yqFW7Ujku6MjWMPfyxUyD",
      "balance": 453556.332754,
      "percentage": 0.05,
      "rank": 29,
      "addedAt": "2025-09-27T07:13:18.504Z",
      "lastSeen": "2025-09-27T07:13:18.504Z",
      "updateCount": 1
    },
    {
      "address": "AvfsD5DM8our3dhYntbKdac6MpFu4WdruCNDbryR1ajS",
      "balance": 430777.808296,
      "percentage": 0.04,
      "rank": 30,
      "addedAt": "2025-09-27T07:13:18.504Z",
      "lastSeen": "2025-09-27T07:13:18.504Z",
      "updateCount": 1
    },
    {
      "address": "CSjfKrSGVuWi2SXUDL9ENyMsU37t3FiHp92bF2FCtKGS",
      "balance": 424144.548012,
      "percentage": 0.04,
      "rank": 31,
      "addedAt": "2025-09-27T07:13:18.504Z",
      "lastSeen": "2025-09-27T07:13:18.504Z",
      "updateCount": 1
    },
    {
      "address": "6m6iReUWyyPoyAycZSBeLpdSVoi6knpgQR22rZsCtERB",
      "balance": 313437.757158,
      "percentage": 0.03,
      "rank": 32,
      "addedAt": "2025-09-27T07:13:18.504Z",
      "lastSeen": "2025-09-27T07:13:18.504Z",
      "updateCount": 1
    },
    {
      "address": "EswHbMthhCZ5pHFbRwE7N469w471YvCs57iDM68XtZqA",
      "balance": 294790.650903,
      "percentage": 0.03,
      "rank": 33,
      "addedAt": "2025-09-27T07:13:18.504Z",
      "lastSeen": "2025-09-27T07:13:18.504Z",
      "updateCount": 1
    },
    {
      "address": "7VFroGmp8AdXkY54QP2xJCb5m9tnsQYJQ8Zm5B7hhEw2",
      "balance": 208443.856721,
      "percentage": 0.02,
      "rank": 34,
      "addedAt": "2025-09-27T07:13:18.504Z",
      "lastSeen": "2025-09-27T07:13:18.504Z",
      "updateCount": 1
    },
    {
      "address": "Hj91pbm3sFWmus5ugDVK4bHPHDppekKGwwou6zxVyw4Y",
      "balance": 191005.004739,
      "percentage": 0.02,
      "rank": 35,
      "addedAt": "2025-09-27T07:13:18.504Z",
      "lastSeen": "2025-09-27T07:13:18.504Z",
      "updateCount": 1
    },
    {
      "address": "2VXZ3zrvPLdy1HfRjbPRECDPZGj22g25Bi6uEfModEsn",
      "balance": 163647.019333,
      "percentage": 0.02,
      "rank": 36,
      "addedAt": "2025-09-27T07:13:18.504Z",
      "lastSeen": "2025-09-27T07:13:18.504Z",
      "updateCount": 1
    },
    {
      "address": "DFkhQDsLLssiCGELgSBiRs7F3AoGuijLzwWXzXGZPnHu",
      "balance": 150000,
      "percentage": 0.01,
      "rank": 37,
      "addedAt": "2025-09-27T07:13:18.504Z",
      "lastSeen": "2025-09-27T07:13:18.504Z",
      "updateCount": 1
    },
    {
      "address": "8psNvWTrdNTiVRNzAgsou9kETXNJm2SXZyaKuJraVRtf",
      "balance": 146483.330051,
      "percentage": 0.01,
      "rank": 38,
      "addedAt": "2025-09-27T07:13:18.504Z",
      "lastSeen": "2025-09-27T07:13:18.504Z",
      "updateCount": 1
    },
    {
      "address": "8wiwkpSsY7XHLJiwr6Wj5nswvxvbMfaXNUjwzjXPXRMx",
      "balance": 117543.237716,
      "percentage": 0.01,
      "rank": 39,
      "addedAt": "2025-09-27T07:13:18.504Z",
      "lastSeen": "2025-09-27T07:13:18.504Z",
      "updateCount": 1
    },
    {
      "address": "BdKbKe77GbpGC7RbrDfEE4PgNrrxoQE9WyCYSQYR9KeH",
      "balance": 108290.077788,
      "percentage": 0.01,
      "rank": 40,
      "addedAt": "2025-09-27T07:13:18.504Z",
      "lastSeen": "2025-09-27T07:13:18.504Z",
      "updateCount": 1
    },
    {
      "address": "6egfD5gWxy8sJX8QbLYu2RzxMSbLa6bPAh7mkgxLFxg2",
      "balance": 104088.319332,
      "percentage": 0.01,
      "rank": 41,
      "addedAt": "2025-09-27T07:13:18.504Z",
      "lastSeen": "2025-09-27T07:13:18.504Z",
      "updateCount": 1
    },
    {
      "address": "9eRGFZmkd3vnTuehUd1URgyhpAppDNJhwuRj9bA1SkJ9",
      "balance": 100406.759401,
      "percentage": 0.01,
      "rank": 42,
      "addedAt": "2025-09-27T07:13:18.504Z",
      "lastSeen": "2025-09-27T07:13:18.504Z",
      "updateCount": 1
    },
    {
      "address": "EDjm5HTGZo98q64mieL9HTbvtkt9ogJECeuAfVqeCgBe",
      "balance": 96698.068034,
      "percentage": 0.01,
      "rank": 43,
      "addedAt": "2025-09-27T07:13:18.504Z",
      "lastSeen": "2025-09-27T07:13:18.504Z",
      "updateCount": 1
    },
    {
      "address": "B9Z5DJTAjWRbwoCtMyB3neUVQyvHv4nJFxzJmxMC5HNR",
      "balance": 90420.656151,
      "percentage": 0.01,
      "rank": 44,
      "addedAt": "2025-09-27T07:13:18.504Z",
      "lastSeen": "2025-09-27T07:13:18.504Z",
      "updateCount": 1
    },
    {
      "address": "HLnpSz9h2S4hiLQ43rnSD9XkcUThA7B8hQMKmDaiTLcC",
      "balance": 85000,
      "percentage": 0.01,
      "rank": 45,
      "addedAt": "2025-09-27T07:13:18.504Z",
      "lastSeen": "2025-09-27T07:13:18.504Z",
      "updateCount": 1
    },
    {
      "address": "FunNU8qjGP3GmkS9qmFdSDki6HkAo5UuqUjnoDr6y15G",
      "balance": 76479.79803,
      "percentage": 0.01,
      "rank": 46,
      "addedAt": "2025-09-27T07:13:18.504Z",
      "lastSeen": "2025-09-27T07:13:18.504Z",
      "updateCount": 1
    },
    {
      "address": "D8sbSZG9h7v9EamkqNPQ1jh5XfGp2GS3Dy31U9c82Eyw",
      "balance": 50297.027454,
      "percentage": 0.01,
      "rank": 47,
      "addedAt": "2025-09-27T07:13:18.504Z",
      "lastSeen": "2025-09-27T07:13:18.504Z",
      "updateCount": 1
    },
    {
      "address": "D9GYt4W7VvteKCSvTgyjzuiBJyTy94Kmr6YiC9fbxGjW",
      "balance": 47864.200921,
      "percentage": 0,
      "rank": 48,
      "addedAt": "2025-09-27T07:13:18.504Z",
      "lastSeen": "2025-09-27T07:13:18.504Z",
      "updateCount": 1
    },
    {
      "address": "G8MoxE8DBmtaLNoyKFqH4BzDVJEScqpaySjSdmJgWvr7",
      "balance": 26677.756676,
      "percentage": 0,
      "rank": 49,
      "addedAt": "2025-09-27T07:13:18.504Z",
      "lastSeen": "2025-09-27T07:13:18.504Z",
      "updateCount": 1
    },
    {
      "address": "D8ZPmpTug5DgVWx2XGotfjUNkAtjfj5MXdbmYmRmyRjS",
      "balance": 24645.858027,
      "percentage": 0,
      "rank": 50,
      "addedAt": "2025-09-27T07:13:18.504Z",
      "lastSeen": "2025-09-27T07:13:18.504Z",
      "updateCount": 1
    },
    {
      "address": "7qy37hn3w3SQTE7U4hZ8oLb8gNCPW14YLXUJMDy1zcNE",
      "balance": 14253.793652,
      "percentage": 0,
      "rank": 51,
      "addedAt": "2025-09-27T07:13:18.504Z",
      "lastSeen": "2025-09-27T07:13:18.504Z",
      "updateCount": 1
    },
    {
      "address": "9gFA7cjcwiz9fNwCDMrjRjbQgMacUpcsTLBifAfGpcur",
      "balance": 12635.679824,
      "percentage": 0,
      "rank": 52,
      "addedAt": "2025-09-27T07:13:18.504Z",
      "lastSeen": "2025-09-27T07:13:18.504Z",
      "updateCount": 1
    },
    {
      "address": "FjqB1dRe2gb2SKMfcq4Z4KUWUUbUyLxGJHmdW24pf6KP",
      "balance": 2453.151263,
      "percentage": 0,
      "rank": 53,
      "addedAt": "2025-09-27T07:13:18.504Z",
      "lastSeen": "2025-09-27T07:13:18.504Z",
      "updateCount": 1
    },
    {
      "address": "HBMtSZD6cdPjrpyrtBuyjFgwBgar9D7GomYB3fjgzuzN",
      "balance": 1768.644741,
      "percentage": 0,
      "rank": 54,
      "addedAt": "2025-09-27T07:13:18.504Z",
      "lastSeen": "2025-09-27T07:13:18.504Z",
      "updateCount": 1
    },
    {
      "address": "9QvQif3WAXn6j7cGEdk5gcmCukAMPtvQzE8t2HxDeMZn",
      "balance": 0.007523,
      "percentage": 0,
      "rank": 55,
      "addedAt": "2025-09-27T07:13:18.504Z",
      "lastSeen": "2025-09-27T07:13:18.504Z",
      "updateCount": 1
    }
  ],
  "currentWallet": {
    "address": "FjqB1dRe2gb2SKMfcq4Z4KUWUUbUyLxGJHmdW24pf6KP",
    "balance": 2453.151263,
    "percentage": 0,
    "rank": 53,
    "addedAt": "2025-09-27T07:13:18.504Z",
    "lastSeen": "2025-09-27T07:13:18.504Z",
    "updateCount": 1,
    "selectedAt": "2025-09-27T07:13:18.506Z"
  },
  "history": [
    {
      "address": "FjqB1dRe2gb2SKMfcq4Z4KUWUUbUyLxGJHmdW24pf6KP",
      "balance": 2453.151263,
      "percentage": 0,
      "rank": 53,
      "timestamp": "2025-09-27T07:13:18.506Z"
    }
  ],
  "stats": {
    "totalRaces": 1,
    "totalWalletsProcessed": 55,
    "lastUpdate": "2025-09-27T07:13:18.504Z",
    "createdAt": "2025-09-27T07:05:20.872Z"
  },
  "metadata": {
    "tokenAddress": "2nzzHWMXD8ismXTcooiW6eML2euKvEZ7T8CPajLXpump",
    "tokenName": "Tu-Token",
    "version": "1.0.0"
  },
  "winners": [],
  "soldWallets": [
    "D1dpuayJLitQmZXb57Xv17BEyh8XRjKrQzgWSkqXAiTa",
    "BevGABL6pJiv34BCxzryRQmTkBW5f4ycKXCVyx7bS7us",
    "CSm22ryK7U3pi5moa86SuKGKqhFAugwqDsPTndkRqBSQ",
    "9qnFZvvCRhY2o3QeiaNujZwXWWF4LhjD3rNcfUPEup1T",
    "HKskSv16yQbjfejK5MptHSNfcXNtykWR5Yr9y6E68wYM",
    "AQyT9cEnqkC6f6LBQzTbvbFDmjjv6HYoUF5PCEFnnDb3"
  ]
}